Workbook

Sheet Summary
A1: Review Dashboard
A3: Total reviews | B3: =COUNTA(Data!$B:$B)-1 -> 2377
A5: Language counts | D5: Aspect counts
A6: Language | B6: Count | D6: Aspect | E6: Mentioned | F6: Positive | G6: Neutral | H6: Negative | I6: Not mentioned
A7: ru | B7: =COUNTIF(Data!$B:$B,A7) -> 1061 | D7: FQ | E7: =COUNTIF(Data!$E:$E,1) -> 1129 | F7: =COUNTIFS(Data!$E:$E,1,Data!$F:$F,"positive") -> 662 | G7: =COUNTIFS(Data!$E:$E,1,Data!$F:$F,"neutral") -> 146 | H7: =COUNTIFS(Data!$E:$E,1,Data!$F:$F,"negative") -> 321 | I7: =COUNTIF(Data!$E:$E,0) -> 1247
A8: kz | B8: =COUNTIF(Data!$B:$B,A8) -> 1003 | D8: SS | E8: =COUNTIF(Data!$G:$G,1) -> 1096 | F8: =COUNTIFS(Data!$G:$G,1,Data!$H:$H,"positive") -> 625 | G8: =COUNTIFS(Data!$G:$G,1,Data!$H:$H,"neutral") -> 70 | H8: =COUNTIFS(Data!$G:$G,1,Data!$H:$H,"negative") -> 401 | I8: =COUNTIF(Data!$G:$G,0) -> 1280
A9: mixed | B9: =COUNTIF(Data!$B:$B,A9) -> 313 | D9: OA | E9: =COUNTIF(Data!$I:$I,1) -> 354 | F9: =COUNTIFS(Data!$I:$I,1,Data!$J:$J,"positive") -> 40 | G9: =COUNTIFS(Data!$I:$I,1,Data!$J:$J,"neutral") -> 77 | H9: =COUNTIFS(Data!$I:$I,1,Data!$J:$J,"negative") -> 237 | I9: =COUNTIF(Data!$I:$I,0) -> 2022
A10: Total | B10: =SUM(B7:B9) -> 2377 | D10: CL | E10: =COUNTIF(Data!$K:$K,1) -> 398 | F10: =COUNTIFS(Data!$K:$K,1,Data!$L:$L,"positive") -> 104 | G10: =COUNTIFS(Data!$K:$K,1,Data!$L:$L,"neutral") -> 91 | H10: =COUNTIFS(Data!$K:$K,1,Data!$L:$L,"negative") -> 203 | I10: =COUNTIF(Data!$K:$K,0) -> 1978
D11: PV | E11: =COUNTIF(Data!$M:$M,1) -> 299 | F11: =COUNTIFS(Data!$M:$M,1,Data!$N:$N,"positive") -> 67 | G11: =COUNTIFS(Data!$M:$M,1,Data!$N:$N,"neutral") -> 54 | H11: =COUNTIFS(Data!$M:$M,1,Data!$N:$N,"negative") -> 178 | I11: =COUNTIF(Data!$M:$M,0) -> 2076
A12: Как читать: | D12: WS | E12: =COUNTIF(Data!$O:$O,1) -> 357 | F12: =COUNTIFS(Data!$O:$O,1,Data!$P:$P,"positive") -> 115 | G12: =COUNTIFS(Data!$O:$O,1,Data!$P:$P,"neutral") -> 27 | H12: =COUNTIFS(Data!$O:$O,1,Data!$P:$P,"negative") -> 215 | I12: =COUNTIF(Data!$O:$O,0) -> 2018
A13: Mentioned = сколько отзывов вообще затрагивают аспект | D13: AM | E13: =COUNTIF(Data!$Q:$Q,1) -> 582 | F13: =COUNTIFS(Data!$Q:$Q,1,Data!$R:$R,"positive") -> 401 | G13: =COUNTIFS(Data!$Q:$Q,1,Data!$R:$R,"neutral") -> 54 | H13: =COUNTIFS(Data!$Q:$Q,1,Data!$R:$R,"negative") -> 127 | I13: =COUNTIF(Data!$Q:$Q,0) -> 1793
A14: Positive / Neutral / Negative = тональность внутри этого аспекта | D14: LO | E14: =COUNTIF(Data!$S:$S,1) -> 274 | F14: =COUNTIFS(Data!$S:$S,1,Data!$T:$T,"positive") -> 103 | G14: =COUNTIFS(Data!$S:$S,1,Data!$T:$T,"neutral") -> 74 | H14: =COUNTIFS(Data!$S:$S,1,Data!$T:$T,"negative") -> 97 | I14: =COUNTIF(Data!$S:$S,0) -> 2100
A15: Примечание:
A16: В части строк review_id пустой, поэтому общий счетчик лучше считать по language или text.
A18: Дополнительно: см. лист "Aspect by Language" для разбивки аспектов по ru / kz / mixed.

Sheet Data
A1: review_id | B1: language | C1: star_rating | D1: text | E1: FQ | F1: FQ_sent | G1: SS | H1: SS_sent | I1: OA | J1: OA_sent | K1: CL | L1: CL_sent | M1: PV | N1: PV_sent | O1: WS | P1: WS_sent | Q1: AM | R1: AM_sent | S1: LO | T1: LO_sent
A2: 1 | B2: ru | C2: 4 | D2: Еда вкусная, персонал вежливый, но заказ ждали слишком долго. | E2: 1 | F2: positive | G2: 1 | H2: positive | I2: 0 | J2: NA | K2: 0 | L2: NA | M2: 0 | N2: NA | O2: 1 | P2: negative | Q2: 0 | R2: NA | S2: 0 | T2: NA
A3: 2 | B3: ru | C3: 2 | D3: В помещении грязно, заказ перепутали, а цена для такого качества завышена. | E3: 0 | F3: NA | G3: 0 | H3: NA | I3: 1 | J3: negative | K3: 1 | L3: negative | M3: 1 | N3: negative | O3: 0 | P3: NA | Q3: 0 | R3: NA | S3: 0 | T3: NA
A4: 3 | B4: ru | C4: 5 | D4: Очень уютное место, удобная локация, кофе свежий и вкусный. | E4: 1 | F4: positive | G4: 0 | H4: NA | I4: 0 | J4: NA | K4: 0 | L4: NA | M4: 0 | N4: NA | O4: 0 | P4: NA | Q4: 1 | R4: positive | S4: 1 | T4: positive
A5: 4 | B5: kz | C5: 3 | D5: Тағам жаман емес, бірақ қызмет баяу және офицанттар көңіл бөлмеді. | E5: 1 | F5: neutral | G5: 1 | H5: negative | I5: 0 | J5: NA | K5: 0 | L5: NA | M5: 0 | N5: NA | O5: 1 | P5: negative | Q5: 0 | R5: NA | S5: 0 | T5: NA
A6: 5 | B6: ru | C6: 5 | D6: очень вкусные бургеры,всем советуюю | E6: 1 | F6: positive | G6: 0 | H6: NA | I6: 0 | J6: NA | K6: 0 | L6: NA | M6: 0 | N6: NA | O6: 0 | P6: NA | Q6: 0 | R6: NA | S6: 0 | T6: NA
A7: 6 | B7: kz | C7: 5 | D7: Тамаша орын! | E7: 0 | F7: NA | G7: 0 | H7: NA | I7: 0 | J7: NA | K7: 0 | L7: NA | M7: 0 | N7: NA | O7: 0 | P7: NA | Q7: 1 | R7: positive | S7: 0 | T7: NA
A8: 7 | B8: kz | C8: 5 | D8: Бүгін түскі асқа Фритос комбо алдым. Тез дайындады. Рахмет | E8: 0 | F8: NA | G8: 0 | H8: NA | I8: 0 | J8: NA | K8: 0 | L8: NA | M8: 0 | N8: NA | O8: 1 | P8: positive | Q8: 0 | R8: NA | S8: 0 | T8: NA
A9: 8 | B9: mixed | C9: 5 | D9: Классический чикен бургер алдым. Тауық еті шырынды, огурчики тұздығы дәмді. Булка жұмсақ. Жалпы ұнады, тағы келемін | E9: 1 | F9: positive | G9: 0 | H9: NA | I9: 0 | J9: NA | K9: 0 | L9: NA | M9: 0 | N9: NA | O9: 0 | P9: NA | Q9: 0 | R9: NA | S9: 0 | T9: NA
A10: 9 | B10: ru | C10: 1 | D10: бургер принесли холодным,хотя ждали почти час,сыр был сырой,худший филиал | E10: 1 | F10: negative | G10: 0 | H10: NA | I10: 0 | J10: NA | K10: 0 | L10: NA | M10: 0 | N10: NA | O10: 1 | P10: negative | Q10: 0 | R10: NA | S10: 0 | T10: NA
A11: 10 | B11: ru | C11: 4 | D11: Самые-самые лучшие пирожки, как дома, всё свежее всегда. | E11: 1 | F11: positive | G11: 0 | H11: NA | I11: 0 | J11: NA | K11: 0 | L11: NA | M11: 0 | N11: NA | O11: 0 | P11: NA | Q11: 0 | R11: NA | S11: 0 | T11: NA
A12: 11 | B12: ru | C12: 5 | D12: Пил кофе и в Риме, и в Париже, но вкуснее, чем капуч на фундучном молоке с фирменными сливками Джинжу, не пробовал ничего! Десерты тоже очень необычные. Ребята-бариста большие молодцы! Что можно улучшить? Маловато места, с посадкой можно что-то придумать? | E12: 1 | F12: positive | G12: 1 | H12: positive | I12: 0 | J12: NA | K12: 0 | L12: NA | M12: 0 | N12: NA | O12: 0 | P12: NA | Q12: 1 | R12: negative | S12: 0 | T12: NA
A13: 12 | B13: ru | C13: 4 | D13: Не очень удобное расположение, от метро идти мин 20 быстрым шагом через промзону. В самом кофе мест очень мало, а желающих очень много(( пирожные очень вкусные, кофе бывает вкуснее. Второй раз именно туда не пойду. | E13: 1 | F13: neutral | G13: 0 | H13: NA | I13: 0 | J13: NA | K13: 0 | L13: NA | M13: 0 | N13: NA | O13: 0 | P13: NA | Q13: 1 | R13: negative | S13: 1 | T13: negative
A14: 13 | B14: ru | C14: 4 | D14: Положительное место с хорошими блюдами, только персонал отличился высокомерием и надменностью, не рекомендую к посещению, останется неприятный осадок. | E14: 1 | F14: positive | G14: 1 | H14: negative | I14: 0 | J14: NA | K14: 0 | L14: NA | M14: 0 | N14: NA | O14: 0 | P14: NA | Q14: 0 | R14: NA | S14: 0 | T14: NA
A15: 14 | B15: ru | C15: 1 | D15: Доставка очень долгая, на рекламной брошюре написано от 500 р доставка бесплатно, а по факту заплатили 100 р за доставку. Чек был на 577 р. Долго плевались от нагара, который был на сковородке с мясом, хруст на зубах неприятен. Испорченное мнение от вашего заведения. | E15: 1 | F15: negative | G15: 0 | H15: NA | I15: 0 | J15: NA | K15: 1 | L15: negative | M15: 1 | N15: negative | O15: 1 | P15: negative | Q15: 0 | R15: NA | S15: 0 | T15: NA
A16: 15 | B16: ru | C16: 5 | D16: Отличная кухня, прекрасный сервис, внимательный персонал. Кафе рекомендую. | E16: 1 | F16: positive | G16: 1 | H16: positive | I16: 0 | J16: NA | K16: 0 | L16: NA | M16: 0 | N16: NA | O16: 0 | P16: NA | Q16: 0 | R16: NA | S16: 0 | T16: NA
A17: 16 | B17: ru | C17: 5 | D17: Очень вкусно! И по-домашнему! Замечательный комплексный обед! Недорого, порции хорошие! | E17: 1 | F17: positive | G17: 0 | H17: NA | I17: 0 | J17: NA | K17: 0 | L17: NA | M17: 1 | N17: positive | O17: 0 | P17: NA | Q17: 0 | R17: NA | S17: 0 | T17: NA
... A153: 152 | B153: kz | C153: 5 | D153: Донері өте дәмді, лавашы жұмсақ, іші құрғақ емес. Қызметкерлер де сыпайы сөйлеп, жақсы әсер қалдырды. | E153: 1 | F153: positive | G153: 1 | H153: positive | I153: 0 | J153: NA | K153: 0 | L153: NA | M153: 0 | N153: NA | O153: 0 | P153: NA | Q153: 0 | R153: NA | S153: 0 | T153: NA
A154: 153 | B154: kz | C154: NA | D154: Тағамдары жаман емес, бірақ ерекше есте қалатындай дәм байқамадым. Бағасы сәл қымбаттау көрінді. | E154: 1 | F154: neutral | G154: 0 | H154: NA | I154: 0 | J154: NA | K154: 0 | L154: NA | M154: 1 | N154: negative | O154: 0 | P154: NA | Q154: 0 | R154: NA | S154: 0 | T154: NA
A155: 154 | B155: kz | C155: NA | D155: Кофесі де, десерті де өте дәмді болды, бәрі жаңа дайындалғаны білініп тұр. Ішіндегі атмосферасы да жайлы екен. | E155: 1 | F155: positive | G155: 0 | H155: NA | I155: 0 | J155: NA | K155: 0 | L155: NA | M155: 0 | N155: NA | O155: 0 | P155: NA | Q155: 1 | R155: positive | S155: 0 | T155: NA
A156: 155 | B156: kz | C156: NA | D156: Тауық еті қаттылау болып шықты, ал гарнирі мүлде суып қалған. Тапсырысты тез әкелгенімен, тағам сапасы ұнамады. | E156: 1 | F156: negative | G156: 0 | H156: NA | I156: 0 | J156: NA | K156: 0 | L156: NA | M156: 0 | N156: NA | O156: 1 | P156: positive | Q156: 0 | R156: NA | S156: 0 | T156: NA
A157: 156 | B157: kz | C157: NA | D157: Мантысы өте дәмді, қамыры жұқа, іші шырынды екен. Порциясы да жақсы, аш келсең тоясың. | E157: 1 | F157: positive | G157: 0 | H157: NA | I157: 0 | J157: NA | K157: 0 | L157: NA | M157: 1 | N157: positive | O157: 0 | P157: NA | Q157: 0 | R157: NA | S157: 0 | T157: NA
A158: 157 | B158: kz | C158: NA | D158: Тағамның дәмі орташа ғана, тұзы сәл көптеу болды. Қызмет көрсету жаман емес, бірақ бұл жердің асханасы онша әсер етпеді. | E158: 1 | F158: negative | G158: 1 | H158: neutral | I158: 0 | J158: NA | K158: 0 | L158: NA | M158: 0 | N158: NA | O158: 0 | P158: NA | Q158: 0 | R158: NA | S158: 0 | T158: NA
A159: 158 | B159: kz | C159: NA | D159: Балық өте жақсы дайындалған, иісі де, дәмі де жаңа екенін байқатты. Тазалығы мен жалпы қызметі де көңілге қонды. | E159: 1 | F159: positive | G159: 1 | H159: positive | I159: 0 | J159: NA | K159: 1 | L159: positive | M159: 0 | N159: NA | O159: 0 | P159: NA | Q159: 0 | R159: NA | S159: 0 | T159: NA
A160: 159 | B160: kz | C160: NA | D160: Бағасына қарасаң, тағам сапасы әлдеқайда жақсы болуы керек еді. Пастасы құрғақ, соусы аз, сондықтан аса ұнамады. | E160: 1 | F160: negative | G160: 0 | H160: NA | I160: 0 | J160: NA | K160: 0 | L160: NA | M160: 1 | N160: negative | O160: 0 | P160: NA | Q160: 0 | R160: NA | S160: 0 | T160: NA
A161: 160 | B161: kz | C161: NA | D161: Өте дәмді тағам екен, әсіресе палауы ұнады, майы да, тұзы да орнымен. Орынның өзі де жайлы, достармен тыныш отырып тамақтануға болады. | E161: 1 | F161: positive | G161: 0 | H161: NA | I161: 0 | J161: NA | K161: 0 | L161: NA | M161: 0 | N161: NA | O161: 0 | P161: NA | Q161: 1 | R161: positive | S161: 0 | T161: NA
A162: 161 | B162: kz | C162: NA | D162: Іші өте таза екен, үстелдер де, еден де жинақы болды. Осындай жерге қайта келгің келеді. | E162: 0 | F162: NA | G162: 0 | H162: NA | I162: 0 | J162: NA | K162: 1 | L162: positive | M162: 0 | N162: NA | O162: 0 | P162: NA | Q162: 0 | R162: NA | S162: 0 | T162: NA
A163: 162 | B163: kz | C163: NA | D163: Жалпы орын жаман емес, бірақ үстел үсті дұрыс сүртілмеген сияқты көрінді. Тамақ дәмді болды, алайда тазалық жағы жақсырақ болса екен. | E163: 1 | F163: positive | G163: 0 | H163: NA | I163: 0 | J163: NA | K163: 1 | L163: negative | M163: 0 | N163: NA | O163: 0 | P163: NA | Q163: 0 | R163: NA | S163: 0 | T163: NA
A164: 163 | B164: kz | C164: NA | D164: Кафенің іші тап-таза, ыдыстары да жылтырап тұр. Қызмет көрсетуімен бірге осы жағы да қатты ұнады. | E164: 0 | F164: NA | G164: 1 | H164: positive | I164: 0 | J164: NA | K164: 1 | L164: positive | M164: 0 | N164: NA | O164: 0 | P164: NA | Q164: 0 | R164: NA | S164: 0 | T164: NA
A165: 164 | B165: kz | C165: NA | D165: Дәретханасы таза болмағаны көңілге тиді. Мұндай жерде тамақтың дәмі жақсы болса да, әсер төмендеп кетеді екен. | E165: 1 | F165: positive | G165: 0 | H165: NA | I165: 0 | J165: NA | K165: 1 | L165: negative | M165: 0 | N165: NA | O165: 0 | P165: NA | Q165: 0 | R165: NA | S165: 0 | T165: NA
... A185: 184 | B185: mixed | C185: NA | D185: Кассир алып тастандаршы жумыстан менсенби турама адамды калай калай ози хиджаб киген кыз | E185: 0 | F185: NA | G185: 1 | H185: negative | I185: 0 | J185: NA | K185: 0 | L185: NA | M185: 0 | N185: NA | O185: 0 | P185: NA | Q185: 0 | R185: NA | S185: 0 | T185: NA
A186: 185 | B186: ru | C186: 5 | D186: В зале чисто, столы аккуратно протерты, находиться внутри приятно. Сразу видно, что за порядком здесь следят. | E186: 0 | F186: NA | G186: 0 | H186: NA | I186: 0 | J186: NA | K186: 1 | L186: positive | M186: 0 | N186: NA | O186: 0 | P186: NA | Q186: 0 | R186: NA | S186: 0 | T186: NA
A187: 186 | B187: ru | C187: 3 | D187: Еда вкусная, но чистота в зале оставила смешанные впечатления: на столе были крошки, и его долго не убирали. | E187: 1 | F187: positive | G187: 0 | H187: NA | I187: 0 | J187: NA | K187: 1 | L187: negative | M187: 0 | N187: NA | O187: 0 | P187: NA | Q187: 0 | R187: NA | S187: 0 | T187: NA
A188: 187 | B188: ru | C188: 5 | D188: Очень понравилось, что в заведении чисто и нет посторонних запахов. В такой атмосфере даже еда кажется еще приятнее. | E188: 0 | F188: NA | G188: 0 | H188: NA | I188: 0 | J188: NA | K188: 1 | L188: positive | M188: 0 | N188: NA | O188: 0 | P188: NA | Q188: 0 | R188: NA | S188: 0 | T188: NA
A189: 188 | B189: ru | C189: 2 | D189: В целом место неплохое, но пол был грязноват, особенно возле столиков. На такие вещи сразу обращаешь внимание. | E189: 0 | F189: NA | G189: 0 | H189: NA | I189: 0 | J189: NA | K189: 1 | L189: negative | M189: 0 | N189: NA | O189: 0 | P189: NA | Q189: 0 | R189: NA | S189: 0 | T189: NA
A190: 189 | B190: ru | C190: 5 | D190: Туалет был чистый, мыло и салфетки на месте, что для меня всегда важно. За это отдельный плюс заведению. | E190: 0 | F190: NA | G190: 0 | H190: NA | I190: 0 | J190: NA | K190: 1 | L190: positive | M190: 0 | N190: NA | O190: 0 | P190: NA | Q190: 0 | R190: NA | S190: 0 | T190: NA
A191: 190 | B191: ru | C191: 4 | D191: Персонал вежливый, заказ принесли быстро, но на подносе остались какие-то пятна. В плане гигиены хотелось бы аккуратнее. | E191: 0 | F191: NA | G191: 1 | H191: positive | I191: 0 | J191: NA | K191: 1 | L191: negative | M191: 0 | N191: NA | O191: 1 | P191: positive | Q191: 0 | R191: NA | S191: 0 | T191: NA
A192: 191 | B192: ru | C192: 5 | D192: Внутри уютно и чисто, посуда без разводов, приборы тоже аккуратные. Оставило хорошее впечатление. | E192: 0 | F192: NA | G192: 0 | H192: NA | I192: 0 | J192: NA | K192: 1 | L192: positive | M192: 0 | N192: NA | O192: 0 | P192: NA | Q192: 0 | R192: NA | S192: 0 | T192: NA
A193: 192 | B193: ru | C193: 4 | D193: Заказ понравился, но стол, за который сели, был плохо протерт. Пришлось просить, чтобы его убрали. | E193: 1 | F193: positive | G193: 0 | H193: NA | I193: 0 | J193: NA | K193: 1 | L193: negative | M193: 0 | N193: NA | O193: 0 | P193: NA | Q193: 0 | R193: NA | S193: 0 | T193: NA
A194: 193 | B194: ru | C194: 5 | D194: В заведении чисто, светло и приятно находиться. Особенно понравилось, что даже в час пик все выглядело опрятно. | E194: 0 | F194: NA | G194: 0 | H194: NA | I194: 0 | J194: NA | K194: 1 | L194: positive | M194: 0 | N194: NA | O194: 0 | P194: NA | Q194: 0 | R194: NA | S194: 0 | T194: NA
A195: 194 | B195: ru | C195: 3 | D195: Не могу сказать, что было грязно, но и идеальной чистоты тоже не заметил. Обычный средний уровень. | E195: 0 | F195: NA | G195: 0 | H195: NA | I195: 0 | J195: NA | K195: 1 | L195: neutral | M195: 0 | N195: NA | O195: 0 | P195: NA | Q195: 0 | R195: NA | S195: 0 | T195: NA
A196: 195 | B196: ru | C196: 5 | D196: На кухню, конечно, не заглянешь, но в зале все выглядело аккуратно и ухоженно. Это вызывает доверие к месту. | E196: 0 | F196: NA | G196: 0 | H196: NA | I196: 0 | J196: NA | K196: 1 | L196: positive | M196: 0 | N196: NA | O196: 0 | P196: NA | Q196: 0 | R196: NA | S196: 0 | T196: NA
A197: 196 | B197: ru | C197: 4 | D197: Еда была нормальная, а вот в туалете чистота подкачала. Для общего впечатления такие детали очень важны. | E197: 1 | F197: neutral | G197: 0 | H197: NA | I197: 0 | J197: NA | K197: 1 | L197: negative | M197: 0 | N197: NA | O197: 0 | P197: NA | Q197: 0 | R197: NA | S197: 0 | T197: NA
... A324: 323 | B324: mixed | C324: 2 | D324: Персоналдар негизи нашар кыздар адамнын кел бетине карап обслуживание жасайды.Бояган сланган кыздар келсе олип кала жаздайды.Барлыгымыз бир Алладан кегенимизди умытпаса екен деймин | E324: 0 | F324: NA | G324: 1 | H324: negative | I324: 0 | J324: NA | K324: 0 | L324: NA | M324: 0 | N324: NA | O324: 0 | P324: NA | Q324: 0 | R324: NA | S324: 0 | T324: NA
A325: 324 | B325: mixed | C325: 1 | D325: Тым жақсы кофейняның шырқын бұзды. Тары кофейнясының ашылғанын ұзақ күткенмін. 22.01.23 жолдасыммен коляскадағы баламмен барғанмын, ішіндегі қызметкерлер, официант, менеджер, администратор өз-өздерімен. Әсіресе адамның сырт келбетіне қарап, қызмет ететіні алаңдатты. Күтіп тұрғанымызға 20мин болды, өзімізбен бірге алдық кофені, бірақ ол кофенің дайын болуына тағы 20мин кетті, 1 кофе 250мл, 2 кофе алдық, счетқа за обслуживание қосып жіберген, соны айтып едім, сол қыздың ақшасын сұрап тұрғанда тарс ете берді чекті. Кофе5/10. Бірақ заведение дизайны , интерьері өте әдемі. Біз капучино тарымен,латте ірімшікпен алдық. Алып баратқан күштілігін көрмедім. Енді бармаспыз деп шештік. | E325: mixed | F325: NA | G325: Кофе нашар, қызмет көрсету сапасы да өте төмен. | H325: 1 | I325: neutral | J325: 1 | K325: negative | L325: 0 | M325: NA | N325: 0 | O325: NA | P325: 1 | Q325: negative | R325: 1 | S325: negative | T325: 1 | U325: positive | V325: 0 | W325: NA
A326: 325 | B326: mixed | C326: 1 | D326: Баршаңызға Қайырлы күн! Төменде барлық кемшіл тұстарды астын сызып отырып жазып кеттім. Кешіріңіздер, алайда еріксіз басқа Қазақтың мынандай мақалы еске түседі екен “Қойшы көп болса-Қой арам өледі деген”. 4-бірдей “Директор” жүр дейді мыс. Төрт келіншек бастығымыз шайды 50-минут қайнатып жүр. (Қызыл көйлек, қара жолақты жейде, көк жейде, жане сары шашты директор) | E326: 0 | F326: NA | G326: 1 | H326: negative | I326: 0 | J326: NA | K326: 0 | L326: NA | M326: 0 | N326: NA | O326: 1 | P326: negative | Q326: 0 | R326: NA | S326: 0 | T326: NA
A327: 326 | B327: kz | C327: 3 | D327: Көкжиек деген шай алдық, ол ұнамады. Құрамы түсініксіз, дәмі не тәтті емес, не қышқыл емес, қысқасы іше алмадық. Жалпы алғанда, мұндай этнокофеханалар ашылғанына өте қуаныштымыз! Қызмет сапасы жақсарып, мәзірдегі тағамдар көбейеді деп үміттенеміз. Іске сәт! | E327: 1 | F327: negative | G327: 1 | H327: negative | I327: 0 | J327: NA | K327: 0 | L327: NA | M327: 0 | N327: NA | O327: 0 | P327: NA | Q327: 1 | R327: positive | S327: 0 | T327: NA
A328: 327 | B328: kz | C328: 2 | D328: Айтпақшы, ас мәзірін қазақшалап қойыңыздаршы, қазақ дәмін орысша оқыған шыны керек біртүрлі екен | E328: 0 | F328: NA | G328: 1 | H328: negative | I328: 0 | J328: NA | K328: 0 | L328: NA | M328: 0 | N328: NA | O328: 0 | P328: NA | Q328: 0 | R328: NA | S328: 0 | T328: NA
A329: 328 | B329: mixed | C329: 3 | D329: Интерьер минимализм стильде. Тамағымызды өте ұзақ күттік. Қуырдақ алуға кеңес бермеймін . Басқа алған тамағымыз дәмді болды | E329: 1 | F329: neutral | G329: 0 | H329: NA | I329: 0 | J329: NA | K329: 0 | L329: NA | M329: 0 | N329: NA | O329: 1 | P329: negative | Q329: 1 | R329: neutral | S329: 0 | T329: NA
A330: 329 | B330: mixed | C330: 3 | D330: Тарыға екінші рет келіп отырмын, бірінші рет Алматыда болғам. Екі ретте де қазақша мәзір жоқ. Техникалық ашылу болды деп түсіндірді, бірақ оның не қатысы бар? Неге орысша дайын онда? Сосын әкімші орысша жауап қатты қазақша сөйлесек. Келесі жолы барғанда, мәзір де болады деп үміттенем. | E330: 0 | F330: NA | G330: 1 | H330: negative | I330: 0 | J330: NA | K330: 0 | L330: NA | M330: 0 | N330: NA | O330: 0 | P330: NA | Q330: 0 | R330: NA | S330: 0 | T330: NA
A331: 330 | B331: kz | C331: 1 | D331: Асханасынын багасы удай, кафе ресторандардын багасын кояды, мешиттин асханасында ,уяттан безгендер, Алладан корыкпайды екен | E331: 0 | F331: NA | G331: 0 | H331: NA | I331: 0 | J331: NA | K331: 0 | L331: NA | M331: 1 | N331: negative | O331: 0 | P331: NA | Q331: 0 | R331: NA | S331: 0 | T331: NA
A332: 331 | B332: kz | C332: 2 | D332: Суши дайындау білмейма, німене. Ұнамады маған | E332: 1 | F332: negative | G332: 0 | H332: NA | I332: 0 | J332: NA | K332: 0 | L332: NA | M332: 0 | N332: NA | O332: 0 | P332: NA | Q332: 0 | R332: NA | S332: 0 | T332: NA
A333: 332 | B333: kz | C333: 1 | D333: Қызмет көрсету сапасы төмен. Шляп-ляп қызмет | E333: 0 | F333: NA | G333: 1 | H333: negative | I333: 0 | J333: NA | K333: 0 | L333: NA | M333: 0 | N333: NA | O333: 0 | P333: NA | Q333: 0 | R333: NA | S333: 0 | T333: NA
A334: 333 | B334: mixed | C334: 2 | D334: Заказ көп уақыт күттік | E334: 0 | F334: NA | G334: 0 | H334: NA | I334: 0 | J334: NA | K334: 0 | L334: NA | M334: 0 | N334: NA | O334: 1 | P334: negative | Q334: 0 | R334: NA | S334: 0 | T334: NA
A335: 334 | B335: mixed | C335: 3 | D335: Суши, донер, пицца сөз жоқ керемет ал өкінішке орай шашлык жеу былай тұрсын тістеу мүмкін емес, Құрметті Шаурма Фуд администраторы түсінеміз кемшіліксіз нәрсе болмайды дегенмен мұндай нәрселерге жоғарғы дәрежеде назар аударсаңыздар дұрыс болар еді. | E335: 1 | F335: neutral | G335: 0 | H335: NA | I335: 0 | J335: NA | K335: 0 | L335: NA | M335: 0 | N335: NA | O335: 0 | P335: NA | Q335: 0 | R335: NA | S335: 0 | T335: NA
A336: 335 | B336: kz | C336: 1 | D336: Аруна жумысын өте жаксы укыпты жасайды екен,әрдайым кулип карсы алады,өте жаксы кыз!осында енді всегда келип турамыз. | E336: 0 | F336: NA | G336: 1 | H336: positive | I336: 0 | J336: NA | K336: 0 | L336: NA | M336: 0 | N336: NA | O336: 0 | P336: NA | Q336: 0 | R336: NA | S336: 0 | T336: NA
A337: 336 | B337: mixed | C337: 3 | D337: Сәлеметсіздерме! Бүгін өзіміз жақсы көретін халал асханасы бар Shaurma Food - қа келдік. Әрқашан мәзірден шаурма немесе суши-ролл алатынбыз. Бүгін басқаша әзірді алып көрдік. Ұнамады. Өте майлы, дәмі тек ащысы бар Том-ям әзірі. Келсеңіздер тек шаурмаға келіңіздер. Бірақ соның өзіндеде шаурмаларыда дәмсіз болып бара жатыр. | E337: 1 | F337: negative | G337: 0 | H337: NA | I337: 0 | J337: NA | K337: 0 | L337: NA | M337: 0 | N337: NA | O337: 0 | P337: NA | Q337: 0 | R337: NA | S337: 0 | T337: NA
... A549: 548 | B549: kz | C549: 5 | D549: Керемет өте дәмді бургерлер тек Бахандиде | E549: 1 | F549: positive | G549: 0 | H549: NA | I549: 0 | J549: NA | K549: 0 | L549: NA | M549: 0 | N549: NA | O549: 0 | P549: NA | Q549: 0 | R549: NA | S549: 0 | T549: NA
A550: 549 | B550: kz | C550: NA | D550: Өте дәмді! Қызмет көрсету сапасы 5! Айдос красавчик! | E550: 1 | F550: positive | G550: 1 | H550: positive | I550: 0 | J550: NA | K550: 0 | L550: NA | M550: 0 | N550: NA | O550: 0 | P550: NA | Q550: 0 | R550: NA | S550: 0 | T550: NA
A551: 550 | B551: kz | C551: NA | D551: Қызмет көрсету жылдам, бургер өте дәмді! | E551: 1 | F551: positive | G551: 1 | H551: positive | I551: 0 | J551: NA | K551: 0 | L551: NA | M551: 0 | N551: NA | O551: 1 | P551: positive | Q551: 0 | R551: NA | S551: 0 | T551: NA
A552: 551 | B552: mixed | C552: NA | D552: Өте дәмді бургерлер! Рақмет, bahandi! Отбасымызбен бірге бургер жеп кетеміз! | E552: 1 | F552: positive | G552: 0 | H552: NA | I552: 0 | J552: NA | K552: 0 | L552: NA | M552: 0 | N552: NA | O552: 0 | P552: NA | Q552: 0 | R552: NA | S552: 0 | T552: NA
A553: 552 | B553: kz | C553: NA | D553: жақсы қызмет көрсетілді.тамаша.Жигиттер жақсы қарсы алып,ойдағыдан аса қызмет көрсетті үлкен рахмет!! | E553: 0 | F553: NA | G553: 1 | H553: positive | I553: 0 | J553: NA | K553: 0 | L553: NA | M553: 0 | N553: NA | O553: 0 | P553: NA | Q553: 0 | R553: NA | S553: 0 | T553: NA
A554: 553 | B554: kz | C554: NA | D554: Керемет Аллах разы болсын | E554: 0 | F554: NA | G554: 0 | H554: NA | I554: 0 | J554: NA | K554: 0 | L554: NA | M554: 0 | N554: NA | O554: 0 | P554: NA | Q554: 1 | R554: positive | S554: 0 | T554: NA
A555: 554 | B555: mixed | C555: NA | D555: Жарты сағат күтіп кофе іше алмадық. Бариста орнында жоқ. Coffe shop басшыларна ескерту беру керек. Абсолютно жарты сағат күттік ешкім келмеді. | E555: 0 | F555: NA | G555: 1 | H555: negative | I555: 0 | J555: NA | K555: 0 | L555: NA | M555: 0 | N555: NA | O555: 1 | P555: negative | Q555: 0 | R555: NA | S555: 0 | T555: NA
A556: 555 | B556: kz | C556: NA | D556: Қызмет көрсетуі өте жоғары Қолжетімді бағада барлық тағамдары! | E556: 0 | F556: NA | G556: 1 | H556: positive | I556: 0 | J556: NA | K556: 0 | L556: NA | M556: 1 | N556: positive | O556: 0 | P556: NA | Q556: 0 | R556: NA | S556: 0 | T556: NA
A557: 556 | B557: mixed | C557: NA | D557: Оте тамаша жер,музыкасы 100%супер,тагамдары,офисанттары оте сыпайы,красавчик админдери оте киши пейл оте сапалы оз жумысынын маманы 100%конилимнен шыкты!!! | E557: 1 | F557: positive | G557: 1 | H557: positive | I557: 0 | J557: NA | K557: 0 | L557: NA | M557: 0 | N557: NA | O557: 0 | P557: NA | Q557: 1 | R557: positive | S557: 0 | T557: NA
A558: 557 | B558: kz | C558: NA | D558: Оте тамаша жер,келгениме окинбедим конактарымда ырза,баринизге баруды кенес беремин. | E558: 0 | F558: NA | G558: 0 | H558: NA | I558: 0 | J558: NA | K558: 0 | L558: NA | M558: 0 | N558: NA | O558: 0 | P558: NA | Q558: 1 | R558: positive | S558: 0 | T558: NA
A559: 558 | B559: kz | C559: NA | D559: Отбасымызбен отырып, керемет әсер алдық, тағамдары өте дәмді, десерттері де керемет, рахмет үлкен, сіздердің тұрақты қонақтарыңыз боламыз | E559: 1 | F559: positive | G559: 0 | H559: NA | I559: 0 | J559: NA | K559: 0 | L559: NA | M559: 0 | N559: NA | O559: 0 | P559: NA | Q559: 1 | R559: positive | S559: 0 | T559: NA
A560: 559 | B560: kz | C560: NA | D560: Каусар шайханасы рақмеет көп көп сіздерге тағамдарыңыз ұнады | E560: 1 | F560: positive | G560: 0 | H560: NA | I560: 0 | J560: NA | K560: 0 | L560: NA | M560: 0 | N560: NA | O560: 0 | P560: NA | Q560: 0 | R560: NA | S560: 0 | T560: NA
A561: 560 | B561: kz | C561: NA | D561: Каусар шайханасы қазақи, әр қашан домыра үні ойналып, шабытыңды ашады тағамға деген | E561: 0 | F561: NA | G561: 0 | H561: NA | I561: 0 | J561: NA | K561: 0 | L561: NA | M561: 0 | N561: NA | O561: 0 | P561: NA | Q561: 1 | R561: positive | S561: 0 | T561: NA
... A603: 602 | B603: kz | C603: NA | D603: Өте дәмді тағамдар, бәрі бізге өте ұнады, тағыда келетін боламыз, даяшы Ұлбала өте әдепті, бағамыз 10/10 | E603: 1 | F603: positive | G603: 1 | H603: positive | I603: 0 | J603: NA | K603: 0 | L603: NA | M603: 0 | N603: NA | O603: 0 | P603: NA | Q603: 0 | R603: NA | S603: 0 | T603: NA
A604: 603 | B604: kz | C604: NA | D604: Тағамдары өте дәмді, тағамды ұсынуы ерекше, сервис ұнады | E604: 1 | F604: positive | G604: 1 | H604: positive | I604: 0 | J604: NA | K604: 0 | L604: NA
A605: 604 | B605: kz | C605: NA | D605: Өте керемет тамақтары супер қызмет көрсету сапасы керемет Сандық мейрам ханаға мың алғыс,Аллах разы болсын сіздерге елімізде осындай мейрамхана көп болсын | E605: 1 | F605: positive | G605: 1 | H605: positive | I605: 0 | J605: NA | K605: 0 | L605: NA | M605: 0 | N605: NA | O605: 0 | P605: NA | Q605: 0 | R605: NA | S605: 0 | T605: NA
A606: 605 | B606: kz | C606: NA | D606: Ассалямуалейкум! Оте Керемет мейрамхана, оте дамди, кызмет корсетуы оте жогары денгейде! Осындай керемет асты буйырткан Алла га сансыз шукир! Дайындаган аспазшыга Рахмет, колыныз дерт кормесин! Осы Казаки накышта мейрамхана ашкан басшысына мын Алгас! | E606: 1 | F606: positive | G606: 1 | H606: positive | I606: 0 | J606: NA | K606: 0 | L606: NA | M606: 0 | N606: NA | O606: 0 | P606: NA | Q606: 1 | R606: positive | S606: 0 | T606: NA
A607: 606 | B607: kz | C607: NA | D607: барлығы ұнады | E607: 0 | F607: NA | G607: 0 | H607: NA | I607: 0 | J607: NA | K607: 0 | L607: NA | M607: 0 | N607: NA | O607: 0 | P607: NA | Q607: 1 | R607: positive | S607: 0 | T607: NA
A608: 607 | B608: kz | C608: NA | D608: Бәрі керемет. Тағамдары өте өте дәмді,сервис жоғары деңгейде. Түркістанда осындай ресторан бар екеніне қуанамыз! | E608: 1 | F608: positive | G608: 1 | H608: positive | I608: 0 | J608: NA | K608: 0 | L608: NA | M608: 0 | N608: NA | O608: 0 | P608: NA | Q608: 1 | R608: positive | S608: 0 | T608: NA
A609: 608 | B609: kz | C609: NA | D609: Құрметті қонақтар осындай керемет мейрамханада ас ішіп әжемді есіме алдым дәл әжем дайындаған Намад көжесін ішіп рахаттандым. Тағамдар өте дәмді керемет махаббат пен дайындалған. | E609: 1 | F609: positive | G609: 0 | H609: NA | I609: 0 | J609: NA | K609: 0 | L609: NA | M609: 0 | N609: NA | O609: 0 | P609: NA | Q609: 1 | R609: positive | S609: 0 | T609: NA
A610: 609 | B610: kz | C610: NA | D610: Алланың нұры жаусын, дайаршы қыздар жігіттер әдемі сыпайы | E610: 0 | F610: NA | G610: 1 | H610: positive | I610: 0 | J610: NA | K610: 0 | L610: NA | M610: 0 | N610: NA | O610: 0 | P610: NA | Q610: 0 | R610: NA | S610: 0 | T610: NA
A611: 610 | B611: kz | C611: NA | D611: Сандықтын тағамдары өте керемет бараңыздар көрініздер | E611: 1 | F611: positive | G611: 0 | H611: NA | I611: 0 | J611: NA | K611: 0 | L611: NA | M611: 0 | N611: NA | O611: 0 | P611: NA | Q611: 0 | R611: NA | S611: 0 | T611: NA
A612: 611 | B612: kz | C612: NA | D612: Өте керемет. Қызмет көрсету сапасы да, тағамдары да, атмосферасы да күшті. | E612: 1 | F612: positive | G612: 1 | H612: positive | I612: 0 | J612: NA | K612: 0 | L612: NA | M612: 0 | N612: NA | O612: 0 | P612: NA | Q612: 1 | R612: positive | S612: 0 | T612: NA
A613: 612 | B613: kz | C613: NA | D613: Бәрі керемет - тамағы дәмді, қызметкерлер сыпайы, интерьер тамаша, музыка мен ән шеруі де өте жақсы. | E613: 1 | F613: positive | G613: 1 | H613: positive | I613: 0 | J613: NA | K613: 0 | L613: NA | M613: 0 | N613: NA | O613: 0 | P613: NA | Q613: 1 | R613: positive | S613: 0 | T613: NA
A614: 613 | B614: kz | C614: NA | D614: Қазақ ұлтының құндылықтарын дәріптеп жатқан Сандық мейрамханасына респект! Тамақтары да өте дәмді , керемет | E614: 1 | F614: positive | G614: 0 | H614: NA | I614: 0 | J614: NA | K614: 0 | L614: NA | M614: 0 | N614: NA | O614: 0 | P614: NA | Q614: 1 | R614: positive | S614: 0 | T614: NA
A615: 614 | B615: kz | C615: NA | D615: мейрамхана “Сандық” қазақтың салт-дәстұрін, колоритін сақтай отырып, еш халыққа еліктемей қонақтарды қуантып, жақсы ниетпен қарсы алады. шет елден келгендерде таң қалып көріпдерін білдіргенін естіп жатыомыз. Осы мейрамхананың барлық қызметкерлеріне алғыс білдіреміз! Рақмет! | E615: 0 | F615: NA | G615: 1 | H615: positive | I615: 0 | J615: NA | K615: 0 | L615: NA | M615: 0 | N615: NA | O615: 0 | P615: NA | Q615: 1 | R615: positive | S615: 0 | T615: NA
A616: 615 | B616: mixed | C616: NA | D616: Рахмет үлкен тамақтары керемет сөзім жоқ бурыңғы ата әжелеріміздің қолынан жегендей әсер алдым барлығы натуральный и полезно денсаулыкка...тіл үйіреді | E616: 1 | F616: positive | G616: 0 | H616: NA | I616: 0 | J616: NA | K616: 0 | L616: NA | M616: 0 | N616: NA | O616: 0 | P616: NA | Q616: 1 | R616: positive | S616: 0 | T616: NA
... A941: 940 | B941: kz | C941: NA | D941: Күшті көңіл ашар орын, балалар алаңы өте тамаша қыздар керемет балаларды сүйгіш екен. Тамаша өтті күніміз рахмет қыздарға | E941: 0 | F941: NA | G941: 1 | H941: positive | I941: 0 | J941: NA | K941: 0 | L941: NA | M941: 0 | N941: NA | O941: 0 | P941: NA | Q941: 1 | R941: positive | S941: 0 | T941: NA
A942: 941 | B942: kz | C942: NA | D942: рахмет тамақтар уақыттылы келді | E942: 0 | F942: NA | G942: 1 | H942: positive | I942: 0 | J942: NA | K942: 0 | L942: NA | M942: 0 | N942: NA | O942: 1 | P942: positive | Q942: 0 | R942: NA
A943: 942 | B943: kz | C943: NA | D943: Қызымның туған күні керемет өтті,тамақтары дәмді. Бізге торт әкеп берген қара киген жігіт пен қызды ерекше атап өткім келеді. Офицанттардың жүздері жылы. Администратор да жақсы адам екен. | E943: 1 | F943: positive | G943: 1 | H943: positive | I943: 0 | J943: NA | K943: 0 | L943: NA | M943: 0 | N943: NA | O943: 0 | P943: NA | Q943: 1 | R943: positive | S943: 0 | T943: NA
A944: 943 | B944: kz | C944: NA | D944: Салем. мырзаға рақмет. Жақсы қызмет көрсетті | E944: 0 | F944: NA | G944: 1 | H944: positive | I944: 0 | J944: NA | K944: 0 | L944: NA | M944: 0 | N944: NA | O944: 0 | P944: NA | Q944: 0 | R944: NA | S944: 0 | T944: NA
A945: 944 | B945: mixed | C945: NA | D945: Тамақтары өте дәмді всегда осында келеміз. Обслуживаниесы жаксы официантқа рахмет жаксы кыз | E945: 1 | F945: positive | G945: 1 | H945: positive | I945: 0 | J945: NA | K945: 0 | L945: NA | M945: 0 | N945: NA | O945: 0 | P945: NA | Q945: 0 | R945: NA | S945: 0 | T945: NA
A946: 945 | B946: mixed | C946: NA | D946: кушти. тамактары дамди. супер | E946: 1 | F946: positive | G946: 0 | H946: NA | I946: 0 | J946: NA | K946: 0 | L946: NA | M946: 0 | N946: NA | O946: 0 | P946: NA | Q946: 1 | R946: positive | S946: 0 | T946: NA
A947: 946 | B947: kz | C947: NA | D947: тамақтары өте дәмді, көп рахмеет | E947: 1 | F947: positive | G947: 1 | H947: positive | I947: 0 | J947: NA | K947: 0 | L947: NA | M947: 0 | N947: NA | O947: 0 | P947: NA | Q947: 0 | R947: NA | S947: 0 | T947: NA
A948: 947 | B948: mixed | C948: NA | D948: Заказдарды өте тез акеледи. даяршы өте шапшаң. Укыпты . Осы жер өте унайды . Тағы келип турамыз . | E948: 0 | F948: NA | G948: 1 | H948: positive | I948: 0 | J948: NA | K948: 0 | L948: NA | M948: 0 | N948: NA | O948: 1 | P948: positive | Q948: 1 | R948: positive | S948: 0 | T948: NA
A949: 948 | B949: mixed | C949: NA | D949: Рахмет коп коп кыздырга рахмет | E949: 0 | F949: NA | G949: 1 | H949: positive | I949: 0 | J949: NA | K949: 0 | L949: NA | M949: 0 | N949: NA | O949: 0 | P949: NA | Q949: 0 | R949: NA | S949: 0 | T949: NA
A950: 949 | B950: kz | C950: NA | D950: офицант, тамақтарыңыз өте дәмді | E950: 1 | F950: positive | G950: 0 | H950: NA | I950: 0 | J950: NA | K950: 0 | L950: NA | M950: 0 | N950: NA | O950: 0 | P950: NA | Q950: 0 | R950: NA | S950: 0 | T950: NA
A951: 950 | B951: kz | C951: NA | D951: өте жаксы қызмет көрсетты | E951: 0 | F951: NA | G951: 1 | H951: positive | I951: 0 | J951: NA | K951: 0 | L951: NA | M951: 0 | N951: NA | O951: 0 | P951: NA | Q951: 0 | R951: NA | S951: 0 | T951: NA
A952: 951 | B952: kz | C952: NA | D952: өте жаксы кызмет корсетті,рахмет | E952: 0 | F952: NA | G952: 1 | H952: positive | I952: 0 | J952: NA | K952: 0 | L952: NA | M952: 0 | N952: NA | O952: 0 | P952: NA | Q952: 0 | R952: NA | S952: 0 | T952: NA
A953: 952 | B953: mixed | C953: NA | D953: Админ көп рақмет!Туған күніміз жоғары деңгейде өтті!Өте керемет,көп көп рақмет!Респект | E953: 0 | F953: NA | G953: 1 | H953: positive | I953: 0 | J953: NA | K953: 0 | L953: NA | M953: 0 | N953: NA | O953: 0 | P953: NA | Q953: 1 | R953: positive | S953: 0 | T953: NA
A954: 953 | B954: kz | C954: NA | D954: Қызмет көрсетуы өте керемет | E954: 0 | F954: NA | G954: 1 | H954: positive | I954: 0 | J954: NA | K954: 0 | L954: NA | M954: 0 | N954: NA | O954: 0 | P954: NA | Q954: 0 | R954: NA | S954: 0 | T954: NA
... A2065: 2064 | B2065: ru | C2065: NA | D2065: Добраться на общественном транспорте сложно, ближайшая остановка далековато. | E2065: 0 | F2065: NA | G2065: 0 | H2065: NA | I2065: 0 | J2065: NA | K2065: 0 | L2065: NA | M2065: 0 | N2065: NA | O2065: 0 | P2065: NA | Q2065: 0 | R2065: NA | S2065: 1 | T2065: negative
A2066: 2065 | B2066: ru | C2066: NA | D2066: Расположение разочаровало: место вроде есть на карте, но на практике найти его было муторно. | E2066: 0 | F2066: NA | G2066: 0 | H2066: NA | I2066: 0 | J2066: NA | K2066: 0 | L2066: NA | M2066: 0 | N2066: NA | O2066: 0 | P2066: NA | Q2066: 0 | S2066: 0 | T2066: NA | U2066: 0 | V2066: NA | W2066: 0 | X2066: NA | Y2066: 0 | Z2066: NA | AA2066: 0 | AB2066: NA | AC2066: 1 | AD2066: negative
...

Sheet Aspect by Language
A1: x`
A3: Как читать: число = сколько отзывов этого языка затрагивают аспект (где аспект = 1).
A5: Aspect by language
A6: Aspect | B6: ru | C6: kz | D6: mixed | E6: Mentioned
A7: FQ | B7: =COUNTIFS(Data!$E:$E,1,Data!$B:$B,B$6) -> 561 | C7: =COUNTIFS(Data!$E:$E,1,Data!$B:$B,C$6) -> 409 | D7: =COUNTIFS(Data!$E:$E,1,Data!$B:$B,D$6) -> 159 | E7: =SUM(B7:D7) -> 1129
A8: SS | B8: =COUNTIFS(Data!$G:$G,1,Data!$B:$B,B$6) -> 458 | C8: =COUNTIFS(Data!$G:$G,1,Data!$B:$B,C$6) -> 426 | D8: =COUNTIFS(Data!$G:$G,1,Data!$B:$B,D$6) -> 212 | E8: =SUM(B8:D8) -> 1096
A9: OA | B9: =COUNTIFS(Data!$I:$I,1,Data!$B:$B,B$6) -> 224 | C9: =COUNTIFS(Data!$I:$I,1,Data!$B:$B,C$6) -> 113 | D9: =COUNTIFS(Data!$I:$I,1,Data!$B:$B,D$6) -> 17 | E9: =SUM(B9:D9) -> 354
A10: CL | B10: =COUNTIFS(Data!$K:$K,1,Data!$B:$B,B$6) -> 212 | C10: =COUNTIFS(Data!$K:$K,1,Data!$B:$B,C$6) -> 160 | D10: =COUNTIFS(Data!$K:$K,1,Data!$B:$B,D$6) -> 26 | E10: =SUM(B10:D10) -> 398
A11: PV | B11: =COUNTIFS(Data!$M:$M,1,Data!$B:$B,B$6) -> 217 | C11: =COUNTIFS(Data!$M:$M,1,Data!$B:$B,C$6) -> 59 | D11: =COUNTIFS(Data!$M:$M,1,Data!$B:$B,D$6) -> 23 | E11: =SUM(B11:D11) -> 299
A12: WS | B12: =COUNTIFS(Data!$O:$O,1,Data!$B:$B,B$6) -> 223 | C12: =COUNTIFS(Data!$O:$O,1,Data!$B:$B,C$6) -> 88 | D12: =COUNTIFS(Data!$O:$O,1,Data!$B:$B,D$6) -> 46 | E12: =SUM(B12:D12) -> 357
A13: AM | B13: =COUNTIFS(Data!$Q:$Q,1,Data!$B:$B,B$6) -> 315 | C13: =COUNTIFS(Data!$Q:$Q,1,Data!$B:$B,C$6) -> 191 | D13: =COUNTIFS(Data!$Q:$Q,1,Data!$B:$B,D$6) -> 76 | E13: =SUM(B13:D13) -> 582
A14: LO | B14: =COUNTIFS(Data!$S:$S,1,Data!$B:$B,B$6) -> 171 | C14: =COUNTIFS(Data!$S:$S,1,Data!$B:$B,C$6) -> 97 | D14: =COUNTIFS(Data!$S:$S,1,Data!$B:$B,D$6) -> 6 | E14: =SUM(B14:D14) -> 274
A15: Total mentions | B15: =SUM(B7:B14) -> 2381 | C15: =SUM(C7:C14) -> 1543 | D15: =SUM(D7:D14) -> 565 | E15: =SUM(E7:E14) -> 4489
A17: Примечание: один отзыв может попадать сразу в несколько аспектов, поэтому "Total mentions" — это сумма упоминаний аспектов, а не уникальных отзывов.
